{
  "_class": "shapePath",
  "booleanOperation": -1,
  "clippingMaskMode": 0,
  "do_objectID": "B6678386-C421-414F-B8AA-E8F18837219B",
  "edited": true,
  "exportOptions": {
    "_class": "exportOptions",
    "do_objectID": "F20CCD38-99D8-4120-9EE4-DF69ECA834A1",
    "exportFormats": [
    ],
    "includedLayerIds": [
    ],
    "layerOptions": 0,
    "shouldTrim": false
  },
  "frame": {
    "_class": "rect",
    "constrainProportions": false,
    "do_objectID": "CA966B22-BE64-43E2-A4B2-1409BB95A99A",
    "height": 1,
    "width": 2.002632606331888,
    "x": 8.768996448881461,
    "y": 0
  },
  "hasClippingMask": false,
  "isClosed": false,
  "isFixedToViewport": false,
  "isFlippedHorizontal": false,
  "isFlippedVertical": false,
  "isLocked": false,
  "isVisible": true,
  "layerListExpandedType": 0,
  "name": "Path",
  "nameIsFixed": false,
  "pointRadiusBehaviour": 0,
  "points": [
    {
      "_class": "curvePoint",
      "cornerRadius": 0,
      "curveFrom": "{0.87156421789105232, 0.016999999999995907}",
      "curveMode": 4,
      "curveTo": "{1, 0.037000000000034561}",
      "hasCurveFrom": true,
      "hasCurveTo": false,
      "point": "{1, 0.037000000000034561}"
    },
    {
      "_class": "curvePoint",
      "cornerRadius": 0,
      "curveFrom": "{0.4092953523238313, 0}",
      "curveMode": 3,
      "curveTo": "{0.74312843578210452, 0}",
      "hasCurveFrom": true,
      "hasCurveTo": true,
      "point": "{0.61469265367315684, 0}"
    },
    {
      "_class": "curvePoint",
      "cornerRadius": 0,
      "curveFrom": "{0, 0.08500000000003638}",
      "curveMode": 4,
      "curveTo": "{0.20389805097450578, 0.033999999999991815}",
      "hasCurveFrom": false,
      "hasCurveTo": true,
      "point": "{0, 0.08500000000003638}"
    }
  ],
  "resizingConstraint": 63,
  "resizingType": 0,
  "rotation": 0,
  "shouldBreakMaskChain": false,
  "style": {
    "_class": "style",
    "endMarkerType": 0,
    "fills": [
      {
        "_class": "fill",
        "color": {
          "_class": "color",
          "alpha": 0,
          "blue": 1,
          "green": 1,
          "red": 1
        },
        "fillType": 0,
        "isEnabled": true,
        "noiseIndex": 0,
        "noiseIntensity": 0,
        "patternFillType": 1,
        "patternTileScale": 1
      }
    ],
    "miterLimit": 10,
    "startMarkerType": 0,
    "windingRule": 1
  }
}