{
  "_class": "symbolInstance",
  "booleanOperation": 0,
  "clippingMaskMode": 0,
  "do_objectID": "A1BD671D-1658-44BA-8156-C32B111DF383",
  "exportOptions": {
    "_class": "exportOptions",
    "do_objectID": "42907F27-F968-4FBF-82D2-9D0E62CA5FB3",
    "exportFormats": [
    ],
    "includedLayerIds": [
    ],
    "layerOptions": 0,
    "shouldTrim": false
  },
  "frame": {
    "_class": "rect",
    "constrainProportions": true,
    "do_objectID": "C2B46741-7004-44AE-8C1D-8BDB0510D141",
    "height": 22,
    "width": 22,
    "x": -1,
    "y": -1
  },
  "hasClippingMask": false,
  "horizontalSpacing": 0,
  "isFixedToViewport": false,
  "isFlippedHorizontal": false,
  "isFlippedVertical": false,
  "isLocked": false,
  "isVisible": true,
  "layerListExpandedType": 0,
  "name": "⚙️Atoms/Colour/Grey Darker",
  "nameIsFixed": false,
  "overrideValues": [
  ],
  "resizingConstraint": 63,
  "resizingType": 0,
  "rotation": 0,
  "scale": 1,
  "shouldBreakMaskChain": false,
  "style": {
    "_class": "style",
    "do_objectID": "58412A01-EB78-4504-A5DD-B80B2C29168B",
    "endMarkerType": 0,
    "miterLimit": 10,
    "startMarkerType": 0,
    "windingRule": 1
  },
  "symbolID": "744B1F84-CE1C-41BC-9E36-54CED997EC2E",
  "verticalSpacing": 0
}