{
  "_class": "symbolInstance",
  "booleanOperation": 0,
  "clippingMaskMode": 0,
  "do_objectID": "7B80064C-3D11-490E-B3EA-469982213660",
  "exportOptions": {
    "_class": "exportOptions",
    "do_objectID": "504F6A87-3E2D-40F8-B2AB-0BC4FD182281",
    "exportFormats": [
    ],
    "includedLayerIds": [
    ],
    "layerOptions": 0,
    "shouldTrim": false
  },
  "frame": {
    "_class": "rect",
    "constrainProportions": false,
    "do_objectID": "5AD5FD6D-8DBA-4AD0-9A75-42856829CE72",
    "height": 10,
    "width": 6,
    "x": 122,
    "y": 14
  },
  "hasClippingMask": false,
  "horizontalSpacing": 0,
  "isFixedToViewport": false,
  "isFlippedHorizontal": false,
  "isFlippedVertical": false,
  "isLocked": false,
  "isVisible": true,
  "layerListExpandedType": 0,
  "name": "Icon/Dropdown Arrow",
  "nameIsFixed": false,
  "overrideValues": [
  ],
  "resizingConstraint": 30,
  "resizingType": 0,
  "rotation": 0,
  "scale": 1,
  "shouldBreakMaskChain": false,
  "style": {
    "_class": "style",
    "do_objectID": "6628EFF7-8329-49C8-A6A1-DD056ABBFA35",
    "endMarkerType": 0,
    "miterLimit": 10,
    "startMarkerType": 0,
    "windingRule": 1
  },
  "symbolID": "24F19309-E1F8-4FE2-A29B-14E61BF98436",
  "verticalSpacing": 0
}