{
  "_class": "text",
  "attributedString": {
    "_class": "attributedString",
    "attributes": [
      {
        "_class": "stringAttribute",
        "attributes": {
          "MSAttributedStringColorAttribute": {
            "_class": "color",
            "alpha": 1,
            "blue": 0.2588235294117647,
            "green": 0.2470588235294118,
            "red": 0.2431372549019608
          },
          "MSAttributedStringFontAttribute": {
            "_class": "fontDescriptor",
            "attributes": {
              "name": "Roboto-Medium",
              "size": 16
            }
          },
          "paragraphStyle": {
            "_class": "paragraphStyle",
            "alignment": 0,
            "allowsDefaultTighteningForTruncation": 0,
            "maximumLineHeight": 24,
            "minimumLineHeight": 24
          }
        },
        "length": 10,
        "location": 0
      }
    ],
    "string": "Jane Pratt"
  },
  "automaticallyDrawOnUnderlyingPath": false,
  "booleanOperation": 0,
  "clippingMaskMode": 0,
  "do_objectID": "378072B2-8126-4344-A857-86C6C708E65B",
  "dontSynchroniseWithSymbol": false,
  "exportOptions": {
    "_class": "exportOptions",
    "do_objectID": "03803B1F-0A3B-4871-BC35-DA252182A742",
    "exportFormats": [
    ],
    "includedLayerIds": [
    ],
    "layerOptions": 0,
    "shouldTrim": false
  },
  "frame": {
    "_class": "rect",
    "constrainProportions": false,
    "do_objectID": "C6897E0F-6748-4492-9400-F254250EAA14",
    "height": 24,
    "width": 74,
    "x": 76,
    "y": 6
  },
  "glyphBounds": "{{0, 5}, {74, 13}}",
  "hasClippingMask": false,
  "isFixedToViewport": false,
  "isFlippedHorizontal": false,
  "isFlippedVertical": false,
  "isLocked": false,
  "isVisible": true,
  "layerListExpandedType": 0,
  "lineSpacingBehaviour": 2,
  "name": "Jane Pratt",
  "nameIsFixed": false,
  "resizingConstraint": 11,
  "resizingType": 0,
  "rotation": 0,
  "sharedStyleID": "7CC8195C-152B-41ED-87FF-EB2CCDCF613B",
  "shouldBreakMaskChain": false,
  "style": {
    "_class": "style",
    "do_objectID": "9BCE2B32-0639-4BFE-9FF2-0E6DDA31E875",
    "endMarkerType": 0,
    "miterLimit": 10,
    "startMarkerType": 0,
    "textStyle": {
      "_class": "textStyle",
      "do_objectID": "6A57FC32-F806-4AAF-9EAE-A282AFBEA82E",
      "encodedAttributes": {
        "MSAttributedStringColorAttribute": {
          "_class": "color",
          "alpha": 1,
          "blue": 0.2588235294117647,
          "green": 0.2470588235294118,
          "red": 0.2431372549019608
        },
        "MSAttributedStringFontAttribute": {
          "_class": "fontDescriptor",
          "attributes": {
            "name": "Roboto-Medium",
            "size": 16
          }
        },
        "paragraphStyle": {
          "_class": "paragraphStyle",
          "alignment": 0,
          "allowsDefaultTighteningForTruncation": 0,
          "maximumLineHeight": 24,
          "minimumLineHeight": 24
        }
      },
      "verticalAlignment": 0
    },
    "windingRule": 1
  },
  "textBehaviour": 0,
  "userInfo": {
    "com.invisionlabs.duplicate": {
      "type-duplicate": {
        "action": "name",
        "options": {
          "gender": "female"
        },
        "title": "Female"
      }
    }
  }
}