{
  "_class": "group",
  "booleanOperation": -1,
  "clippingMaskMode": 0,
  "do_objectID": "0300D936-D5C7-4D6D-A128-88DB6A4CB894",
  "exportOptions": {
    "_class": "exportOptions",
    "exportFormats": [
    ],
    "includedLayerIds": [
    ],
    "layerOptions": 0,
    "shouldTrim": false
  },
  "frame": {
    "_class": "rect",
    "constrainProportions": false,
    "height": 90,
    "width": 1110,
    "x": 0,
    "y": 180
  },
  "hasClickThrough": false,
  "hasClippingMask": false,
  "isFixedToViewport": false,
  "isFlippedHorizontal": false,
  "isFlippedVertical": false,
  "isLocked": false,
  "isVisible": true,
  "layerListExpandedType": 0,
  "layers": [
    {
      "class": "symbolInstance",
      "id": "FDAC2EF3-F1F7-4F8B-B8AA-42214B8BD2C8"
    },
    {
      "class": "group",
      "id": "CF0A9889-FE59-4CD6-8941-295457AC0560"
    },
    {
      "class": "group",
      "id": "3F1F03F5-685E-4E0D-8745-2A5E7DF94891"
    }
  ],
  "name": "📦Other/Table/12col/Appsinator Item",
  "nameIsFixed": true,
  "resizingConstraint": 63,
  "resizingType": 0,
  "rotation": 0,
  "shouldBreakMaskChain": false,
  "style": {
    "_class": "style",
    "endMarkerType": 0,
    "miterLimit": 10,
    "startMarkerType": 0,
    "windingRule": 1
  }
}