{
  "_class": "text",
  "attributedString": {
    "_class": "attributedString",
    "attributes": [
      {
        "_class": "stringAttribute",
        "attributes": {
          "MSAttributedStringColorAttribute": {
            "_class": "color",
            "alpha": 1,
            "blue": 0.6477200255102041,
            "green": 0.6273254319039406,
            "red": 0.6205272340351861
          },
          "MSAttributedStringFontAttribute": {
            "_class": "fontDescriptor",
            "attributes": {
              "name": "Roboto-Regular",
              "size": 14
            }
          },
          "paragraphStyle": {
            "_class": "paragraphStyle",
            "alignment": 1,
            "allowsDefaultTighteningForTruncation": 0,
            "maximumLineHeight": 22,
            "minimumLineHeight": 22
          }
        },
        "length": 3,
        "location": 0
      }
    ],
    "string": "154"
  },
  "automaticallyDrawOnUnderlyingPath": false,
  "booleanOperation": 0,
  "clippingMaskMode": 0,
  "do_objectID": "3F731314-1283-4997-B6B7-BE9AE3FC4681",
  "dontSynchroniseWithSymbol": false,
  "exportOptions": {
    "_class": "exportOptions",
    "do_objectID": "9B1EA072-0B23-4A13-81C4-B0A064F8AF7B",
    "exportFormats": [
    ],
    "includedLayerIds": [
    ],
    "layerOptions": 0,
    "shouldTrim": false
  },
  "frame": {
    "_class": "rect",
    "constrainProportions": false,
    "do_objectID": "6811128D-5494-430D-8873-8929DD027697",
    "height": 22,
    "width": 23.99999999999989,
    "x": 296.0000000000004,
    "y": 19
  },
  "glyphBounds": "{{1, 5}, {23, 12}}",
  "hasClippingMask": false,
  "isFixedToViewport": false,
  "isFlippedHorizontal": false,
  "isFlippedVertical": false,
  "isLocked": false,
  "isVisible": true,
  "layerListExpandedType": 0,
  "lineSpacingBehaviour": 2,
  "name": "154",
  "nameIsFixed": false,
  "resizingConstraint": 46,
  "resizingType": 0,
  "rotation": 0,
  "sharedStyleID": "64959BB3-D114-4F9C-8667-363DF5878877",
  "shouldBreakMaskChain": false,
  "style": {
    "_class": "style",
    "do_objectID": "5715998E-0237-4DCB-87EB-E1208A102FC9",
    "endMarkerType": 0,
    "miterLimit": 10,
    "startMarkerType": 0,
    "textStyle": {
      "_class": "textStyle",
      "do_objectID": "392D376C-85F0-45EE-B7A4-2E9DD25F6684",
      "encodedAttributes": {
        "MSAttributedStringColorAttribute": {
          "_class": "color",
          "alpha": 1,
          "blue": 0.6477200255102041,
          "green": 0.6273254319039406,
          "red": 0.6205272340351861
        },
        "MSAttributedStringFontAttribute": {
          "_class": "fontDescriptor",
          "attributes": {
            "name": "Roboto-Regular",
            "size": 14
          }
        },
        "paragraphStyle": {
          "_class": "paragraphStyle",
          "alignment": 1,
          "allowsDefaultTighteningForTruncation": 0,
          "maximumLineHeight": 22,
          "minimumLineHeight": 22
        }
      },
      "verticalAlignment": 0
    },
    "windingRule": 1
  },
  "textBehaviour": 1
}