{
  "_class": "group",
  "booleanOperation": 0,
  "clippingMaskMode": 0,
  "do_objectID": "195E19C3-9FB9-48A4-92C4-BA4879B37C23",
  "exportOptions": {
    "_class": "exportOptions",
    "do_objectID": "E0274937-65A5-49F9-8881-0F9B7A0766BA",
    "exportFormats": [
    ],
    "includedLayerIds": [
    ],
    "layerOptions": 0,
    "shouldTrim": false
  },
  "frame": {
    "_class": "rect",
    "constrainProportions": false,
    "do_objectID": "6B370257-44CD-4F60-9B66-91E936FA2EF6",
    "height": 22,
    "width": 66,
    "x": 95,
    "y": 111
  },
  "hasClickThrough": false,
  "hasClippingMask": false,
  "isFixedToViewport": false,
  "isFlippedHorizontal": false,
  "isFlippedVertical": false,
  "isLocked": false,
  "isVisible": true,
  "layerListExpandedType": 0,
  "layers": [
    {
      "class": "text",
      "id": "1EF85BEC-05A1-4095-AF2A-EF140574D6D8"
    },
    {
      "class": "symbolInstance",
      "id": "9720A7FC-D75C-43A7-A8E3-3C0BABDC1824"
    }
  ],
  "name": "Progress",
  "nameIsFixed": true,
  "resizingConstraint": 61,
  "resizingType": 0,
  "rotation": 0,
  "shouldBreakMaskChain": false,
  "style": {
    "_class": "style",
    "do_objectID": "174D623A-5CF7-450D-AECC-2A686F9ED306",
    "endMarkerType": 0,
    "miterLimit": 10,
    "startMarkerType": 0,
    "windingRule": 1
  }
}