{
  "_class": "group",
  "booleanOperation": 0,
  "clippingMaskMode": 0,
  "do_objectID": "4D3E4850-867C-4427-927C-B01F00E1A991",
  "exportOptions": {
    "_class": "exportOptions",
    "do_objectID": "17331399-AC12-4BAE-AE2F-AF5A1441B490",
    "exportFormats": [
    ],
    "includedLayerIds": [
    ],
    "layerOptions": 0,
    "shouldTrim": false
  },
  "frame": {
    "_class": "rect",
    "constrainProportions": false,
    "do_objectID": "E27EE2BA-9F3E-4687-8C2B-241A96B68F3E",
    "height": 357,
    "width": 255,
    "x": 870,
    "y": 564
  },
  "hasClickThrough": false,
  "hasClippingMask": false,
  "isFixedToViewport": false,
  "isFlippedHorizontal": false,
  "isFlippedVertical": false,
  "isLocked": false,
  "isVisible": true,
  "layerListExpandedType": 0,
  "layers": [
    {
      "class": "rectangle",
      "id": "8A67E479-D08F-40D7-8421-0469520D319B"
    },
    {
      "class": "group",
      "id": "CB6AB551-1B54-47EE-A2AE-EEAB2D24D694"
    },
    {
      "class": "symbolInstance",
      "id": "64A935C0-58BB-4C2D-85EE-CF07D97B515B"
    }
  ],
  "name": "Pages",
  "nameIsFixed": true,
  "resizingConstraint": 63,
  "resizingType": 0,
  "rotation": 0,
  "shouldBreakMaskChain": false,
  "style": {
    "_class": "style",
    "do_objectID": "45ED6D27-5191-4F28-B356-DC411F20C1CE",
    "endMarkerType": 0,
    "miterLimit": 10,
    "startMarkerType": 0,
    "windingRule": 1
  }
}