{
  "_class": "group",
  "booleanOperation": 0,
  "clippingMaskMode": 0,
  "do_objectID": "1FBB08EF-5A26-4F23-BBD0-9E5D7018266A",
  "exportOptions": {
    "_class": "exportOptions",
    "exportFormats": [
    ],
    "includedLayerIds": [
    ],
    "layerOptions": 0,
    "shouldTrim": false
  },
  "frame": {
    "_class": "rect",
    "constrainProportions": false,
    "height": 1090,
    "width": 285,
    "x": 1155,
    "y": 70
  },
  "hasClickThrough": false,
  "hasClippingMask": false,
  "isFixedToViewport": false,
  "isFlippedHorizontal": false,
  "isFlippedVertical": false,
  "isLocked": false,
  "isVisible": true,
  "layerListExpandedType": 0,
  "layers": [
    {
      "class": "rectangle",
      "id": "CF8659E5-54CB-424F-9856-D089BAEAE48D"
    },
    {
      "class": "group",
      "id": "B782393A-8A3C-4B02-A9DD-A925460947F9"
    },
    {
      "class": "text",
      "id": "1D6D11B5-BA80-4532-A8DB-6F90CB38FD96"
    }
  ],
  "name": "Activity",
  "nameIsFixed": true,
  "resizingConstraint": 63,
  "resizingType": 0,
  "rotation": 0,
  "shouldBreakMaskChain": false,
  "style": {
    "_class": "style",
    "endMarkerType": 0,
    "miterLimit": 10,
    "startMarkerType": 0,
    "windingRule": 1
  }
}