{
  "_class": "group",
  "booleanOperation": 0,
  "clippingMaskMode": 0,
  "do_objectID": "0EF0FEE9-2677-446A-A5F5-AE88822A040A",
  "exportOptions": {
    "_class": "exportOptions",
    "do_objectID": "A7D1D126-5915-4340-A9D5-1A8DA4DF4C15",
    "exportFormats": [
    ],
    "includedLayerIds": [
    ],
    "layerOptions": 0,
    "shouldTrim": false
  },
  "frame": {
    "_class": "rect",
    "constrainProportions": false,
    "do_objectID": "6F67875D-3809-4F4A-A67B-C2F1151A017D",
    "height": 1083,
    "width": 730,
    "x": 300,
    "y": 100
  },
  "hasClickThrough": false,
  "hasClippingMask": false,
  "isFixedToViewport": false,
  "isFlippedHorizontal": false,
  "isFlippedVertical": false,
  "isLocked": false,
  "isVisible": true,
  "layerListExpandedType": 0,
  "layers": [
    {
      "class": "group",
      "id": "1D00C506-FF59-4043-B4B7-4FE506EF77C9"
    },
    {
      "class": "symbolInstance",
      "id": "C177D449-1DA1-4F0E-8016-AB66E7981A78"
    },
    {
      "class": "symbolInstance",
      "id": "C9BAB2E8-0521-4A22-8781-B290E7ECD1C5"
    },
    {
      "class": "symbolInstance",
      "id": "B7E71CA7-D9DF-420A-9756-0525630E45C3"
    },
    {
      "class": "symbolInstance",
      "id": "B766DD30-67A5-4DD4-940F-4DF298407C91"
    },
    {
      "class": "symbolInstance",
      "id": "C4BE2996-540A-47A8-A8FF-4E41656C1BAB"
    },
    {
      "class": "symbolInstance",
      "id": "E63EAE75-B175-4040-9643-D637730EBEC0"
    },
    {
      "class": "symbolInstance",
      "id": "C9E890AC-9934-4A30-9F8C-9FD406A77739"
    },
    {
      "class": "symbolInstance",
      "id": "867659CA-1774-439A-B39C-E2DB43D72131"
    },
    {
      "class": "symbolInstance",
      "id": "9142BC15-2104-4224-BF03-7D57C14571E4"
    }
  ],
  "name": "People",
  "nameIsFixed": true,
  "resizingConstraint": 63,
  "resizingType": 0,
  "rotation": 0,
  "shouldBreakMaskChain": false,
  "style": {
    "_class": "style",
    "do_objectID": "7D614CBF-D3C6-48B3-A01C-FBB587687B39",
    "endMarkerType": 0,
    "miterLimit": 10,
    "startMarkerType": 0,
    "windingRule": 1
  }
}