{
  "_class": "group",
  "booleanOperation": -1,
  "clippingMaskMode": 0,
  "do_objectID": "2E7560AE-00FA-45A6-8BA0-1EFDA5558101",
  "exportOptions": {
    "_class": "exportOptions",
    "exportFormats": [
    ],
    "includedLayerIds": [
    ],
    "layerOptions": 0,
    "shouldTrim": false
  },
  "frame": {
    "_class": "rect",
    "constrainProportions": false,
    "height": 70,
    "width": 1110.000000000001,
    "x": -4.547473508864641e-13,
    "y": 70
  },
  "hasClickThrough": false,
  "hasClippingMask": false,
  "isFixedToViewport": false,
  "isFlippedHorizontal": false,
  "isFlippedVertical": false,
  "isLocked": false,
  "isVisible": true,
  "layerListExpandedType": 0,
  "layers": [
    {
      "class": "symbolInstance",
      "id": "1A50E779-3D68-4DD5-8AB5-498DD9211994"
    },
    {
      "class": "text",
      "id": "37FE81A6-5398-4049-9FB0-8B310C305E1E"
    },
    {
      "class": "text",
      "id": "D9FB1F84-FC44-466B-AC87-59940C1AA97D"
    },
    {
      "class": "text",
      "id": "0A9BBCB7-FC2F-46AB-9241-9DE848B972E1"
    },
    {
      "class": "text",
      "id": "398457E5-DE6F-4809-B248-5E638CD71783"
    },
    {
      "class": "text",
      "id": "CC64418D-7F36-4545-9DFF-95A20A16E10E"
    },
    {
      "class": "text",
      "id": "1EA4DC2B-2C35-4330-BE09-18379CF784F3"
    },
    {
      "class": "text",
      "id": "3C322B96-18D8-4150-9E64-F287073F8E87"
    },
    {
      "class": "text",
      "id": "C9F30F37-9A35-4F23-AA8B-A0E33CC27C13"
    },
    {
      "class": "text",
      "id": "00FBF293-5414-4BE9-8559-2FC9655DA583"
    },
    {
      "class": "symbolInstance",
      "id": "636F52B3-9FB9-438D-8115-92E2EBDBBF34"
    },
    {
      "class": "symbolInstance",
      "id": "84D9350D-DD36-468B-A192-525800D4F61B"
    },
    {
      "class": "symbolInstance",
      "id": "1F7FAAAF-69EE-4182-A0B6-BF5C2B373A5D"
    }
  ],
  "name": "Item",
  "nameIsFixed": true,
  "resizingConstraint": 63,
  "resizingType": 0,
  "rotation": 0,
  "shouldBreakMaskChain": false,
  "style": {
    "_class": "style",
    "endMarkerType": 0,
    "miterLimit": 10,
    "startMarkerType": 0,
    "windingRule": 1
  }
}