{
  "_class": "group",
  "booleanOperation": 0,
  "clippingMaskMode": 0,
  "do_objectID": "06F8EFCE-AA04-463B-8956-129A927B4FAC",
  "exportOptions": {
    "_class": "exportOptions",
    "exportFormats": [
    ],
    "includedLayerIds": [
    ],
    "layerOptions": 0,
    "shouldTrim": false
  },
  "frame": {
    "_class": "rect",
    "constrainProportions": false,
    "height": 122,
    "width": 20,
    "x": 0,
    "y": 40
  },
  "hasClickThrough": false,
  "hasClippingMask": false,
  "isFixedToViewport": false,
  "isFlippedHorizontal": false,
  "isFlippedVertical": false,
  "isLocked": false,
  "isVisible": true,
  "layerListExpandedType": 0,
  "layers": [
    {
      "class": "symbolInstance",
      "id": "D7E12079-F7B6-4316-A4BF-0D02B0944331"
    },
    {
      "class": "symbolInstance",
      "id": "F2AC4764-0FA4-417C-A7D9-4CE79F0354A8"
    },
    {
      "class": "symbolInstance",
      "id": "44C71634-B205-4E05-9BCB-2609DA748D16"
    },
    {
      "class": "symbolInstance",
      "id": "3130130A-E90A-48F8-A4BF-959E2D5CDF6A"
    }
  ],
  "name": "Icons",
  "nameIsFixed": true,
  "resizingConstraint": 27,
  "resizingType": 0,
  "rotation": 0,
  "shouldBreakMaskChain": false,
  "style": {
    "_class": "style",
    "endMarkerType": 0,
    "miterLimit": 10,
    "startMarkerType": 0,
    "windingRule": 1
  }
}