{
  "_class": "group",
  "booleanOperation": 0,
  "clippingMaskMode": 0,
  "do_objectID": "7EF623D7-15EB-4941-B1DB-4AFD68C9D4CD",
  "exportOptions": {
    "_class": "exportOptions",
    "do_objectID": "7CCB8537-A08D-4E7F-AF0C-2287C1EEF3D8",
    "exportFormats": [
    ],
    "includedLayerIds": [
    ],
    "layerOptions": 0,
    "shouldTrim": false
  },
  "frame": {
    "_class": "rect",
    "constrainProportions": false,
    "do_objectID": "B8906956-3AA4-4616-A588-889E7ACC2738",
    "height": 22,
    "width": 89,
    "x": 54,
    "y": 0
  },
  "hasClickThrough": false,
  "hasClippingMask": false,
  "isFixedToViewport": false,
  "isFlippedHorizontal": false,
  "isFlippedVertical": false,
  "isLocked": false,
  "isVisible": true,
  "layerListExpandedType": 0,
  "layers": [
    {
      "class": "text",
      "id": "3872BB83-31A0-46BD-B288-677443419FF1"
    }
  ],
  "name": "Name",
  "nameIsFixed": true,
  "resizingConstraint": 27,
  "resizingType": 0,
  "rotation": 0,
  "shouldBreakMaskChain": false,
  "style": {
    "_class": "style",
    "do_objectID": "F8922995-444F-4343-A0F3-72650B1EFFE4",
    "endMarkerType": 0,
    "miterLimit": 10,
    "startMarkerType": 0,
    "windingRule": 1
  }
}