{
  "_class": "shapePath",
  "booleanOperation": -1,
  "clippingMaskMode": 0,
  "do_objectID": "36F82CFE-45C2-40E9-B411-9D440A697B8D",
  "edited": true,
  "exportOptions": {
    "_class": "exportOptions",
    "do_objectID": "B72C4018-DC01-4D2D-ACC2-92F54FFC8591",
    "exportFormats": [
    ],
    "includedLayerIds": [
    ],
    "layerOptions": 0,
    "shouldTrim": false
  },
  "frame": {
    "_class": "rect",
    "constrainProportions": false,
    "height": 22,
    "width": 98,
    "x": 0,
    "y": 0
  },
  "hasClippingMask": false,
  "isClosed": true,
  "isFixedToViewport": false,
  "isFlippedHorizontal": false,
  "isFlippedVertical": false,
  "isLocked": false,
  "isVisible": true,
  "layerListExpandedType": 0,
  "name": "Graph",
  "nameIsFixed": true,
  "pointRadiusBehaviour": 1,
  "points": [
    {
      "_class": "curvePoint",
      "cornerRadius": 0,
      "curveFrom": "{0, 0.42682379616540128}",
      "curveMode": 1,
      "curveTo": "{0, 0.42682379616540128}",
      "hasCurveFrom": false,
      "hasCurveTo": false,
      "point": "{0, 0.40909090909090906}"
    },
    {
      "_class": "curvePoint",
      "cornerRadius": 0,
      "curveFrom": "{0.090544725815263585, 0.68843227758384729}",
      "curveMode": 1,
      "curveTo": "{0.090544725815263585, 0.68843227758384729}",
      "hasCurveFrom": false,
      "hasCurveTo": false,
      "point": "{0.091836734693877556, 0.68181818181818177}"
    },
    {
      "_class": "curvePoint",
      "cornerRadius": 0,
      "curveFrom": "{0.18209145563854323, 0.58277893302990247}",
      "curveMode": 1,
      "curveTo": "{0.18209145563854323, 0.58277893302990247}",
      "hasCurveFrom": false,
      "hasCurveTo": false,
      "point": "{0.18367346938775511, 0.59090909090909094}"
    },
    {
      "_class": "curvePoint",
      "cornerRadius": 0,
      "curveFrom": "{0.2726361814538068, 0.090909090909090884}",
      "curveMode": 1,
      "curveTo": "{0.2726361814538068, 0.090909090909090884}",
      "hasCurveFrom": false,
      "hasCurveTo": false,
      "point": "{0.27551020408163263, 0.090909090909090884}"
    },
    {
      "_class": "curvePoint",
      "cornerRadius": 0,
      "curveFrom": "{0.36318090726908897, 0.022446160707793893}",
      "curveMode": 1,
      "curveTo": "{0.36318090726908897, 0.022446160707793893}",
      "hasCurveFrom": false,
      "hasCurveTo": false,
      "point": "{0.36734693877551022, 0}"
    },
    {
      "_class": "curvePoint",
      "cornerRadius": 0,
      "curveFrom": "{0.4547276370923678, 0.34171465605321322}",
      "curveMode": 1,
      "curveTo": "{0.4547276370923678, 0.34171465605321322}",
      "hasCurveFrom": false,
      "hasCurveTo": false,
      "point": "{0.45918367346938777, 0.36363636363636365}"
    },
    {
      "_class": "curvePoint",
      "cornerRadius": 0,
      "curveFrom": "{0.54527236290763137, 0.19167495225289138}",
      "curveMode": 1,
      "curveTo": "{0.54527236290763137, 0.19167495225289138}",
      "hasCurveFrom": false,
      "hasCurveTo": false,
      "point": "{0.54081632653061229, 0.18181818181818182}"
    },
    {
      "_class": "curvePoint",
      "cornerRadius": 0,
      "curveFrom": "{0.63681909273091086, 0.72726128750653829}",
      "curveMode": 1,
      "curveTo": "{0.63681909273091086, 0.72726128750653829}",
      "hasCurveFrom": false,
      "hasCurveTo": false,
      "point": "{0.63265306122448983, 0.72727272727272751}"
    },
    {
      "_class": "curvePoint",
      "cornerRadius": 0,
      "curveFrom": "{0.7273638185461746, 0.31817609829872412}",
      "curveMode": 1,
      "curveTo": "{0.7273638185461746, 0.31817609829872412}",
      "hasCurveFrom": false,
      "hasCurveTo": false,
      "point": "{0.72448979591836737, 0.31818181818181818}"
    },
    {
      "_class": "curvePoint",
      "cornerRadius": 0,
      "curveFrom": "{0.81790854436145677, 0.49186984212081114}",
      "curveMode": 1,
      "curveTo": "{0.81790854436145677, 0.49186984212081114}",
      "hasCurveFrom": false,
      "hasCurveTo": false,
      "point": "{0.81632653061224492, 0.5}"
    },
    {
      "_class": "curvePoint",
      "cornerRadius": 0,
      "curveFrom": "{0.90945527418471783, 0.59752318667475623}",
      "curveMode": 1,
      "curveTo": "{0.90945527418471783, 0.59752318667475623}",
      "hasCurveFrom": false,
      "hasCurveTo": false,
      "point": "{0.90816326530612246, 0.59090909090909094}"
    },
    {
      "_class": "curvePoint",
      "cornerRadius": 0,
      "curveFrom": "{1, 0.1995510688926741}",
      "curveMode": 1,
      "curveTo": "{1, 0.1995510688926741}",
      "hasCurveFrom": false,
      "hasCurveTo": false,
      "point": "{1, 0.18181818181818185}"
    },
    {
      "_class": "curvePoint",
      "cornerRadius": 0,
      "curveFrom": "{0.99999999999999589, 0.99999999999999978}",
      "curveMode": 1,
      "curveTo": "{0.99999999999999589, 0.99999999999999978}",
      "hasCurveFrom": false,
      "hasCurveTo": false,
      "point": "{1, 1}"
    },
    {
      "_class": "curvePoint",
      "cornerRadius": 0,
      "curveFrom": "{0.0003030643190098973, 0.99999999999999911}",
      "curveMode": 1,
      "curveTo": "{0.0003030643190098973, 0.99999999999999911}",
      "hasCurveFrom": false,
      "hasCurveTo": false,
      "point": "{0, 1}"
    }
  ],
  "resizingConstraint": 63,
  "resizingType": 0,
  "rotation": 0,
  "shouldBreakMaskChain": false,
  "style": {
    "_class": "style",
    "blur": {
      "_class": "blur",
      "center": "{0.5, 0.5}",
      "do_objectID": "B0307C5A-D504-4A10-84BA-7C376994F41E",
      "isEnabled": false,
      "motionAngle": 0,
      "radius": 0.975975975975976,
      "saturation": 1,
      "type": 0
    },
    "contextSettings": {
      "_class": "graphicsContextSettings",
      "blendMode": 0,
      "do_objectID": "9D94E50B-E1ED-4ECF-8BCA-4EF7F2E5DEAC",
      "opacity": 0.1017410700874669
    },
    "do_objectID": "B5349DB6-F458-4B5B-B509-D409C6611052",
    "endMarkerType": 0,
    "fills": [
      {
        "_class": "fill",
        "color": {
          "_class": "color",
          "alpha": 1,
          "blue": 0.8470588235294118,
          "green": 0.3960784313725493,
          "red": 0.08627450980392158
        },
        "fillType": 0,
        "gradient": {
          "_class": "gradient",
          "elipseLength": 0,
          "from": "{0.018876259647672811, 0.49671426985175438}",
          "gradientType": 0,
          "stops": [
            {
              "_class": "gradientStop",
              "color": {
                "_class": "color",
                "alpha": 1,
                "blue": 0.9215686274509803,
                "green": 0.5686274509803922,
                "red": 0.09803921568627455
              },
              "position": 0
            },
            {
              "_class": "gradientStop",
              "color": {
                "_class": "color",
                "alpha": 1,
                "blue": 0.9725490196078431,
                "green": 0.6313725490196076,
                "red": 0.1764705882352942
              },
              "position": 1
            }
          ],
          "to": "{0.98112374035232708, 0.49671426985175443}"
        },
        "isEnabled": true,
        "noiseIndex": 0,
        "noiseIntensity": 0,
        "patternFillType": 1,
        "patternTileScale": 1
      }
    ],
    "miterLimit": 10,
    "startMarkerType": 0,
    "windingRule": 1
  }
}