{
  "_class": "symbolInstance",
  "booleanOperation": -1,
  "clippingMaskMode": 0,
  "do_objectID": "A1992C74-0EAE-4950-89B0-4D0209BF141D",
  "exportOptions": {
    "_class": "exportOptions",
    "do_objectID": "F12A00AE-7A39-44B8-AFDB-8FAC3F4A865F",
    "exportFormats": [
    ],
    "includedLayerIds": [
    ],
    "layerOptions": 0,
    "shouldTrim": false
  },
  "frame": {
    "_class": "rect",
    "constrainProportions": false,
    "do_objectID": "A466761E-AE9A-4D0F-B4F7-26C5DC63B4DF",
    "height": 251,
    "width": 350,
    "x": 380,
    "y": 562
  },
  "hasClippingMask": false,
  "horizontalSpacing": 0,
  "isFixedToViewport": false,
  "isFlippedHorizontal": false,
  "isFlippedVertical": false,
  "isLocked": false,
  "isVisible": true,
  "layerListExpandedType": 0,
  "name": "📦Other/Building Elements/Other/Person Widget (Search Results) Copy 5",
  "nameIsFixed": false,
  "overrideValues": [
    {
      "_class": "overrideValue",
      "do_objectID": "EE6EA183-998E-4406-8436-A349FA6D7AF1",
      "overrideName": "1FABF929-49AA-4BCC-97E0-775C6B0D2B0A_stringValue",
      "value": "Barry Griffith"
    },
    {
      "_class": "overrideValue",
      "do_objectID": "309F3CED-F405-4CCC-8D32-A41DD6FE3F87",
      "overrideName": "123BE34C-4E58-441E-93AD-A441CF78D829_stringValue",
      "value": "Lead Designer at Google"
    },
    {
      "_class": "overrideValue",
      "do_objectID": "0FBF5202-015F-4E7B-9546-57915106688E",
      "overrideName": "52E37C32-DC55-45C5-9993-1913A259BBF6/7EF1F5A0-860A-490E-A662-D7540B7E4633_symbolID",
      "value": "7C8765D0-B861-4F4C-B29A-D52419EDC6C9"
    },
    {
      "_class": "overrideValue",
      "do_objectID": "5FF88564-A507-4758-850D-8359B7891AB4",
      "overrideName": "0768DAEC-0725-4781-9087-9640BA3C5745_image",
      "value": {
        "_class": "MSJSONFileReference",
        "_ref": "images/52fe11d67900e3550031f46cf8f2209dc9afddc2.png",
        "_ref_class": "MSImageData"
      }
    },
    {
      "_class": "overrideValue",
      "do_objectID": "B6A597B8-80C2-424C-8D17-B81224D6370E",
      "overrideName": "DA615AF1-7B89-4E29-A025-3451CA763AEF_image",
      "value": {
        "_class": "MSJSONFileReference",
        "_ref": "images/a162cf6878b39eea5e93d3412f402c8707f50d72.png",
        "_ref_class": "MSImageData"
      }
    },
    {
      "_class": "overrideValue",
      "do_objectID": "16A2A002-7A41-4105-A1EF-240BE2B07BC1",
      "overrideName": "E89495EF-1542-4C52-B11C-5ACD9E74F562_image",
      "value": {
        "_class": "MSJSONFileReference",
        "_ref": "images/1cb8ff8563c66685f43ed1f15425866530f84536.png",
        "_ref_class": "MSImageData"
      }
    },
    {
      "_class": "overrideValue",
      "do_objectID": "983DF9A4-9846-4528-A976-E3A243896743",
      "overrideName": "1EF0235C-950F-4298-9A6A-9BF0547742FD_stringValue",
      "value": "2 Projects  •  18 Stocks"
    }
  ],
  "resizingConstraint": 63,
  "resizingType": 0,
  "rotation": 0,
  "scale": 1,
  "shouldBreakMaskChain": false,
  "style": {
    "_class": "style",
    "do_objectID": "9A474DE3-6640-48B8-8B7D-E6C6ACF9FC82",
    "endMarkerType": 0,
    "miterLimit": 10,
    "startMarkerType": 0,
    "windingRule": 1
  },
  "symbolID": "3E6D2BB2-87C3-4E5D-A792-C7461FBB8927",
  "verticalSpacing": 0
}