{
  "_class": "text",
  "attributedString": {
    "_class": "attributedString",
    "attributes": [
      {
        "_class": "stringAttribute",
        "attributes": {
          "MSAttributedStringColorAttribute": {
            "_class": "color",
            "alpha": 1,
            "blue": 0.6477200255102041,
            "green": 0.6273254319039406,
            "red": 0.6205272340351861
          },
          "MSAttributedStringFontAttribute": {
            "_class": "fontDescriptor",
            "attributes": {
              "name": "Roboto-Medium",
              "size": 20
            }
          },
          "paragraphStyle": {
            "_class": "paragraphStyle",
            "alignment": 2,
            "allowsDefaultTighteningForTruncation": 0,
            "maximumLineHeight": 30,
            "minimumLineHeight": 30
          }
        },
        "length": 16,
        "location": 0
      }
    ],
    "string": "Rice on the rise"
  },
  "automaticallyDrawOnUnderlyingPath": false,
  "booleanOperation": 0,
  "clippingMaskMode": 0,
  "do_objectID": "CFC5EF08-1294-412F-8CCA-4256D7190784",
  "dontSynchroniseWithSymbol": false,
  "exportOptions": {
    "_class": "exportOptions",
    "do_objectID": "64570A5A-1B3F-4684-A246-4BFDCC500422",
    "exportFormats": [
    ],
    "includedLayerIds": [
    ],
    "layerOptions": 0,
    "shouldTrim": false
  },
  "frame": {
    "_class": "rect",
    "constrainProportions": false,
    "do_objectID": "FD56D6EC-29B9-4AFE-AB4B-E5C6202AA23B",
    "height": 30,
    "width": 138,
    "x": 1.5,
    "y": 84
  },
  "glyphBounds": "{{1, 7}, {137, 16}}",
  "hasClippingMask": false,
  "isFixedToViewport": false,
  "isFlippedHorizontal": false,
  "isFlippedVertical": false,
  "isLocked": false,
  "isVisible": true,
  "layerListExpandedType": 0,
  "lineSpacingBehaviour": 2,
  "name": "20px/Medium/Grey 50%/Centered",
  "nameIsFixed": false,
  "resizingConstraint": 47,
  "resizingType": 0,
  "rotation": 0,
  "sharedStyleID": "F021C914-FFEC-4535-8C73-8911F019CBF5",
  "shouldBreakMaskChain": false,
  "style": {
    "_class": "style",
    "do_objectID": "3F2F7D67-10C0-4874-86AE-E02B800EA879",
    "endMarkerType": 0,
    "miterLimit": 10,
    "startMarkerType": 0,
    "textStyle": {
      "_class": "textStyle",
      "do_objectID": "F99D40CA-2A64-43EA-BA31-4C597F3D39A8",
      "encodedAttributes": {
        "MSAttributedStringColorAttribute": {
          "_class": "color",
          "alpha": 1,
          "blue": 0.6477200255102041,
          "green": 0.6273254319039406,
          "red": 0.6205272340351861
        },
        "MSAttributedStringFontAttribute": {
          "_class": "fontDescriptor",
          "attributes": {
            "name": "Roboto-Medium",
            "size": 20
          }
        },
        "paragraphStyle": {
          "_class": "paragraphStyle",
          "alignment": 2,
          "allowsDefaultTighteningForTruncation": 0,
          "maximumLineHeight": 30,
          "minimumLineHeight": 30
        }
      },
      "verticalAlignment": 0
    },
    "windingRule": 1
  },
  "textBehaviour": 0
}