{
  "_class": "group",
  "booleanOperation": -1,
  "clippingMaskMode": 0,
  "do_objectID": "829858D4-AD92-4164-8EAB-FD4640FCA363",
  "exportOptions": {
    "_class": "exportOptions",
    "do_objectID": "BB8AC9B1-B50D-4F1D-A89C-3F609EC5F521",
    "exportFormats": [
    ],
    "includedLayerIds": [
    ],
    "layerOptions": 0,
    "shouldTrim": false
  },
  "frame": {
    "_class": "rect",
    "constrainProportions": false,
    "do_objectID": "E4AA4816-4B4A-41DE-884E-A2BCFC9CE518",
    "height": 28,
    "width": 28,
    "x": 34,
    "y": 0
  },
  "hasClickThrough": false,
  "hasClippingMask": false,
  "isFixedToViewport": false,
  "isFlippedHorizontal": false,
  "isFlippedVertical": false,
  "isLocked": false,
  "isVisible": true,
  "layerListExpandedType": 0,
  "layers": [
    {
      "class": "oval",
      "id": "8CA7BB64-DF75-4518-818F-B5E7AE7950C5"
    },
    {
      "class": "shapePath",
      "id": "BEB0B6BB-D942-4838-B5E7-E7C747727958"
    }
  ],
  "name": "Plus",
  "nameIsFixed": true,
  "resizingConstraint": 9,
  "resizingType": 0,
  "rotation": 0,
  "shouldBreakMaskChain": false,
  "style": {
    "_class": "style",
    "do_objectID": "9BD9D4E6-EB5E-45E2-8216-87C14E5B9993",
    "endMarkerType": 0,
    "miterLimit": 10,
    "startMarkerType": 0,
    "windingRule": 1
  }
}