{
  "_class": "group",
  "booleanOperation": -1,
  "clippingMaskMode": 0,
  "do_objectID": "23157613-9E5E-47C4-B7FD-1AE27574AD95",
  "exportOptions": {
    "_class": "exportOptions",
    "exportFormats": [
    ],
    "includedLayerIds": [
    ],
    "layerOptions": 0,
    "shouldTrim": false
  },
  "frame": {
    "_class": "rect",
    "constrainProportions": false,
    "height": 49,
    "width": 163,
    "x": 30,
    "y": 406
  },
  "hasClickThrough": false,
  "hasClippingMask": false,
  "isFixedToViewport": false,
  "isFlippedHorizontal": false,
  "isFlippedVertical": false,
  "isLocked": false,
  "isVisible": true,
  "layerListExpandedType": 0,
  "layers": [
    {
      "class": "text",
      "id": "9652938A-0C67-4311-B947-B4D975A6330A"
    },
    {
      "class": "shapeGroup",
      "id": "1D206106-7B7C-4773-8E5D-A1033E161B72"
    },
    {
      "class": "text",
      "id": "99EB2009-A26F-4F77-BAC7-BF503DC7C60E"
    }
  ],
  "name": "Todo",
  "nameIsFixed": true,
  "resizingConstraint": 27,
  "resizingType": 0,
  "rotation": 0,
  "shouldBreakMaskChain": false,
  "style": {
    "_class": "style",
    "endMarkerType": 0,
    "miterLimit": 10,
    "startMarkerType": 0,
    "windingRule": 1
  }
}