{
  "_class": "symbolInstance",
  "booleanOperation": 0,
  "clippingMaskMode": 0,
  "do_objectID": "63262E33-7B93-4EF3-A9C9-24D7FBB85C9F",
  "exportOptions": {
    "_class": "exportOptions",
    "do_objectID": "EE99BE6A-25BF-4B20-8E8D-E2651B9D4911",
    "exportFormats": [
    ],
    "includedLayerIds": [
    ],
    "layerOptions": 0,
    "shouldTrim": false
  },
  "frame": {
    "_class": "rect",
    "constrainProportions": true,
    "do_objectID": "1B1FC9EA-F9EE-401D-8A38-30FA3D555AD4",
    "height": 22,
    "width": 22,
    "x": -1,
    "y": -1
  },
  "hasClippingMask": false,
  "horizontalSpacing": 0,
  "isFixedToViewport": false,
  "isFlippedHorizontal": false,
  "isFlippedVertical": false,
  "isLocked": false,
  "isVisible": true,
  "layerListExpandedType": 0,
  "name": "⚙️Atoms/Colour/Grey Darker",
  "nameIsFixed": false,
  "overrideValues": [
  ],
  "resizingConstraint": 63,
  "resizingType": 0,
  "rotation": 0,
  "scale": 1,
  "shouldBreakMaskChain": false,
  "style": {
    "_class": "style",
    "do_objectID": "22E8E6C0-E9DD-4BE7-9099-B6ACE5423C4B",
    "endMarkerType": 0,
    "miterLimit": 10,
    "startMarkerType": 0,
    "windingRule": 1
  },
  "symbolID": "744B1F84-CE1C-41BC-9E36-54CED997EC2E",
  "verticalSpacing": 0
}